zobar/__init__.py
zobar-0.2.0.dist-info/licenses/LICENSE
zobar-0.2.0.dist-info/METADATA
zobar-0.2.0.dist-info/WHEEL
zobar-0.2.0.dist-info/top_level.txt
zobar-0.2.0.dist-info/RECORD
