Metadata-Version: 2.4
Name: zobar
Version: 0.2.0
Summary: Zero-dependency, high-performance progress bar for HPC and workstations
Author-email: Vishnuvardhan Reddy <vvr3ddy@proton.me>
License: MIT License
Project-URL: Homepage, https://github.com/vvr3ddy/zobar
Project-URL: Bug Tracker, https://github.com/vvr3ddy/zobar/issues
Keywords: progress,bar,cli,terminal,hpc,zero-dependency
Classifier: Development Status :: 5 - Production/Stable
Classifier: Intended Audience :: Developers
Classifier: Intended Audience :: Science/Research
Classifier: License :: OSI Approved :: MIT License
Classifier: Programming Language :: Python :: 3
Classifier: Programming Language :: Python :: 3 :: Only
Classifier: Topic :: System :: Shells
Classifier: Topic :: Terminals
Classifier: Topic :: Utilities
Requires-Python: >=3.7
License-File: LICENSE
Dynamic: license-file
